pymhihvac/__init__.py
pymhihvac/api.py
pymhihvac/const.py
pymhihvac/controller.py
pymhihvac/device.py
pymhihvac/mappings.py
pymhihvac/utils.py
pymhihvac-0.1.2.dist-info/licenses/LICENSE
pymhihvac-0.1.2.dist-info/METADATA
pymhihvac-0.1.2.dist-info/WHEEL
pymhihvac-0.1.2.dist-info/top_level.txt
pymhihvac-0.1.2.dist-info/RECORD
