Metadata-Version: 2.4
Name: pymhihvac
Version: 0.1.2
Summary: Python library to interact with Mitsubishi Heavy Industries HVAC systems
Author-email: coserotondo <cose.rotondo@gmail.com>
License-Expression: MIT
Project-URL: Homepage, https://github.com/coserotondo/pymhihvac
Classifier: Programming Language :: Python :: 3
Classifier: Operating System :: OS Independent
Requires-Python: >=3.8
License-File: LICENSE
Requires-Dist: aiohttp>=3.8.0
Requires-Dist: voluptuous>=0.13.0
Dynamic: license-file
